ocdsindex/__init__.py
ocdsindex/__main__.py
ocdsindex/allow.py
ocdsindex/crawler.py
ocdsindex/exceptions.py
ocdsindex/extract.py
ocdsindex-0.2.0.dist-info/LICENSE
ocdsindex-0.2.0.dist-info/METADATA
ocdsindex-0.2.0.dist-info/WHEEL
ocdsindex-0.2.0.dist-info/entry_points.txt
ocdsindex-0.2.0.dist-info/top_level.txt
ocdsindex-0.2.0.dist-info/RECORD
